{
  "keymapShowTopRow": false,
  "type": "iso",
  "keys": {
    "row1": [
      "`~",
      "1!",
      "2@",
      "3#",
      "4$",
      "5%",
      "6¨",
      "7&",
      "8*",
      "9(",
      "0)",
      "[{",
      "]}"
    ],
    "row2": [
      "kK",
      "yY",
      "oO",
      "uU",
      "'\"",
      "vV",
      "dD",
      "lL",
      "pP",
      "wW",
      "/?",
      "|"
    ],
    "row3": [
      "hH",
      "iI",
      "eE",
      "aA",
      "-_",
      "cC",
      "sS",
      "tT",
      "nN",
      "rR",
      "xX",
      "\\"
    ],
    "row4": ["qQ", "jJ", ",<", ".>", ";:", "fF", "gG", "mM", "bB", "zZ", "=+"],
    "row5": [" "]
  }
}
